jugemaj/__init__.py
jugemaj/admin.py
jugemaj/apps.py
jugemaj/forms.py
jugemaj/migrations/0001_initial.py
jugemaj/migrations/__init__.py
jugemaj/models.py
jugemaj/templates/form.html
jugemaj/templates/jugemaj/bar.html
jugemaj/templates/jugemaj/election_detail.html
jugemaj/templates/jugemaj/election_form.html
jugemaj/templates/jugemaj/election_list.html
jugemaj/templates/jugemaj/namedcandidate_form.html
jugemaj/templates/jugemaj/vote.html
jugemaj/templatetags/__init__.py
jugemaj/templatetags/jugemaj.py
jugemaj/tests.py
jugemaj/urls.py
jugemaj/views.py
django_jugemaj-2.0.1.dist-info/LICENSE
django_jugemaj-2.0.1.dist-info/WHEEL
django_jugemaj-2.0.1.dist-info/METADATA
django_jugemaj-2.0.1.dist-info/RECORD
