Metadata-Version: 2.1
Name: django-jugemaj
Version: 2.0.1
Summary: A Django app for the Majority Judgment voting system
Home-page: https://github.com/nim65s/django-jugemaj
License: BSD-2-Clause
Author: Guilhem Saurel
Author-email: guilhem.saurel@laas.fr
Requires-Python: >=3.6.1,<4.0.0
Classifier: Environment :: Web Environment
Classifier: Framework :: Django
Classifier: Intended Audience :: Developers
Classifier: License :: OSI Approved :: BSD License
Classifier: Operating System :: OS Independent
Classifier: Programming Language :: Python
Classifier: Programming Language :: Python :: 3
Classifier: Programming Language :: Python :: 3.6
Classifier: Programming Language :: Python :: 3.7
Classifier: Programming Language :: Python :: 3.8
Classifier: Topic :: Internet :: WWW/HTTP
Classifier: Topic :: Internet :: WWW/HTTP :: Dynamic Content
Requires-Dist: ndh (>=3.10.4,<4.0.0)
